cmflib/__init__.py
cmflib/cmf.py
cmflib/cmf_commands_wrapper.py
cmflib/cmf_exception_handling.py
cmflib/cmf_federation.py
cmflib/cmf_merger.py
cmflib/cmf_ray_logger.py
cmflib/cmf_server.py
cmflib/cmfquery.py
cmflib/dvc_wrapper.py
cmflib/graph_wrapper.py
cmflib/metadata_helper.py
cmflib/mlmd_objects.py
cmflib/bin/__init__.py
cmflib/bin/cmf
cmflib/bin/cmf_dvc_ingest.py
cmflib/cli/__init__.py
cmflib/cli/command.py
cmflib/cli/parser.py
cmflib/cli/utils.py
cmflib/commands/__init__.py
cmflib/commands/artifact/__init__.py
cmflib/commands/artifact/list.py
cmflib/commands/artifact/pull.py
cmflib/commands/artifact/push.py
cmflib/commands/dvc/__init__.py
cmflib/commands/dvc/ingest.py
cmflib/commands/execution/__init__.py
cmflib/commands/execution/list.py
cmflib/commands/init/__init__.py
cmflib/commands/init/amazonS3.py
cmflib/commands/init/local.py
cmflib/commands/init/minioS3.py
cmflib/commands/init/osdfremote.py
cmflib/commands/init/show.py
cmflib/commands/init/sshremote.py
cmflib/commands/metadata/__init__.py
cmflib/commands/metadata/export.py
cmflib/commands/metadata/pull.py
cmflib/commands/metadata/push.py
cmflib/commands/pipeline/__init__.py
cmflib/commands/pipeline/list.py
cmflib/commands/repo/__init__.py
cmflib/commands/repo/pull.py
cmflib/commands/repo/push.py
cmflib/server_interface/__init__.py
cmflib/server_interface/server_interface.py
cmflib/storage_backends/__init__.py
cmflib/storage_backends/amazonS3_artifacts.py
cmflib/storage_backends/local_artifacts.py
cmflib/storage_backends/minio_artifacts.py
cmflib/storage_backends/osdf_artifacts.py
cmflib/storage_backends/sshremote_artifacts.py
cmflib/store/__init__.py
cmflib/store/cmfstore.py
cmflib/store/postgres.py
cmflib/store/sqllite_store.py
cmflib/utils/__init__.py
cmflib/utils/cmf_config.py
cmflib/utils/dvc_config.py
cmflib/utils/helper_functions.py
cmflib-0.0.97.data/scripts/cmf
server/__init__.py
server/app/__init__.py
server/app/get_data.py
server/app/main.py
server/app/query_artifact_lineage_d3force.py
cmflib-0.0.97.dist-info/METADATA
cmflib-0.0.97.dist-info/WHEEL
cmflib-0.0.97.dist-info/top_level.txt
cmflib-0.0.97.dist-info/RECORD
