Metadata-Version: 2.4
Name: cmflib
Version: 0.0.97
Summary: Track metadata for AI pipeline
Author: Hewlett Packard Enterprise
Project-URL: Homepage, https://github.com/HewlettPackard/cmf
Project-URL: BugTracker, https://github.com/HewlettPackard/cmf/issues
Classifier: Programming Language :: Python :: 3
Classifier: Operating System :: POSIX :: Linux
Requires-Python: <3.12,>=3.9
Requires-Dist: ml-metadata==1.15.0
Requires-Dist: dvc[s3,ssh]==3.51.1
Requires-Dist: pandas
Requires-Dist: retrying
Requires-Dist: pyarrow
Requires-Dist: neo4j==5.26
Requires-Dist: tabulate
Requires-Dist: click
Requires-Dist: minio
Requires-Dist: paramiko==3.4.1
Requires-Dist: scikit_learn
Requires-Dist: scitokens
Requires-Dist: cryptography
Requires-Dist: ray==2.34.0
Requires-Dist: readchar
Requires-Dist: protobuf<5,>=4.25
